[
  {
    "id": "e172ce62-e678-4f64-b79b-bfa19a295b8a",
    "user_id": "c24ccbfe-b964-4c85-8708-0fc86a4e07a8",
    "contract_id": "531a43c9-9c59-4f49-ac09-a374e10420ec",
    "type": "Gerador de energia",
    "model": null,
    "serial_number": null,
    "location": "AVENIDA MACHADO SAN",
    "manufacturer": null,
    "observations": null,
    "quantity": 1,
    "created_at": "2025-12-22T16:05:11.855076-03:00",
    "updated_at": "2025-12-22T16:05:11.855076-03:00",
    "installation_date": null,
    "year": null,
    "condition": "usado",
    "power": "180 kVA",
    "voltage": "220V"
  },
  {
    "id": "ff23d38f-f941-4721-b6f6-de759946a8b5",
    "user_id": "c24ccbfe-b964-4c85-8708-0fc86a4e07a8",
    "contract_id": "50b9fb75-b685-4518-9e7b-ef602930ce32",
    "type": "Gerador de energia elétrica",
    "model": "Não especificado",
    "serial_number": "Não especificado",
    "location": "Sede da CBF (Avenida Luís Carlos Prestes, 130, Barra da Tijuca, Rio de Janeiro/RJ), Superior Tribunal de Justiça Desportiva do Futebol - STJD (Rua Uruguaiana, nº 55, 10 andar, Centro, Rio de Janeiro/RJ), e Granja Comary (Av. Hercílio Ferreira dos Santos, Carlos Guinle, Teresópolis/RJ)",
    "manufacturer": "Não especificado",
    "observations": null,
    "quantity": 1,
    "created_at": "2025-12-22T17:27:27.544933-03:00",
    "updated_at": "2025-12-22T17:27:27.544933-03:00",
    "installation_date": null,
    "year": "Não especificado",
    "condition": "Não especificado",
    "power": "Não especificado",
    "voltage": "Não especificado"
  },
  {
    "id": "94a98a29-b87a-481c-9d9c-fa6a343adc89",
    "user_id": "c24ccbfe-b964-4c85-8708-0fc86a4e07a8",
    "contract_id": "31e69d1c-8a98-4708-8224-83e2ec23cd15",
    "type": "Gerador",
    "model": "Não informado",
    "serial_number": "Não informado",
    "location": "Base da CONTRATANTE na Rua Benedito Otoni, 102, São Cristóvão, Rio de Janeiro/RJ",
    "manufacturer": "Não informado",
    "observations": null,
    "quantity": 1,
    "created_at": "2025-12-29T16:22:08.441602-03:00",
    "updated_at": "2025-12-29T16:22:08.441602-03:00",
    "installation_date": null,
    "year": "Não informado",
    "condition": "Não informado",
    "power": "Não informado",
    "voltage": "Não informado"
  },
  {
    "id": "2e31e1df-3fdd-4fc8-9edc-22424a948d80",
    "user_id": "c24ccbfe-b964-4c85-8708-0fc86a4e07a8",
    "contract_id": "61cfdb33-3a50-4b4c-95dd-51e77203d30c",
    "type": "Gerador",
    "model": "N/A",
    "serial_number": "N/A",
    "location": "Rod. Washington Luiz, S/N, Jardim Primavera, Duque de Caxias, RJ",
    "manufacturer": "N/A",
    "observations": null,
    "quantity": 1,
    "created_at": "2025-12-29T16:24:25.838038-03:00",
    "updated_at": "2025-12-29T16:24:25.838038-03:00",
    "installation_date": null,
    "year": "N/A",
    "condition": "Perfeito estado de uso",
    "power": "2x 550 kVA, 2x 1000 kVA",
    "voltage": "220V"
  },
  {
    "id": "6672daaa-3d8d-4af5-9e0c-a9b27f188054",
    "user_id": "c24ccbfe-b964-4c85-8708-0fc86a4e07a8",
    "contract_id": "0e9ba162-7886-4e39-90ee-03a6085bb5dc",
    "type": "Gerador",
    "model": null,
    "serial_number": null,
    "location": "Endereço do cliente",
    "manufacturer": null,
    "observations": null,
    "quantity": 1,
    "created_at": "2025-12-29T16:26:13.239168-03:00",
    "updated_at": "2025-12-29T16:26:13.239168-03:00",
    "installation_date": null,
    "year": null,
    "condition": "Usado",
    "power": "25 kVA",
    "voltage": "220V"
  },
  {
    "id": "fd7c8f37-2d86-4307-ace2-cfacebec96d2",
    "user_id": "c24ccbfe-b964-4c85-8708-0fc86a4e07a8",
    "contract_id": "9ae3feca-7dd7-4d47-912d-87825b69df98",
    "type": "Gerador de Energia Elétrica",
    "model": "Não informado",
    "serial_number": "Não informado",
    "location": "Estr. da Ilha, 870 - Guaratiba, Rio de Janeiro - RJ, 23020-230",
    "manufacturer": "Não informado",
    "observations": null,
    "quantity": 1,
    "created_at": "2025-12-29T16:31:57.698682-03:00",
    "updated_at": "2025-12-29T16:31:57.698682-03:00",
    "installation_date": null,
    "year": "Não informado",
    "condition": "Perfeitas condições de uso",
    "power": "55 kVA",
    "voltage": "220V"
  },
  {
    "id": "f8e88e21-98db-45cf-b2f8-62a53623b48a",
    "user_id": "c24ccbfe-b964-4c85-8708-0fc86a4e07a8",
    "contract_id": "ada7ff5d-c80f-437c-be8d-6a1eebe863e2",
    "type": "Gerador de Energia Elétrica",
    "model": "230-001",
    "serial_number": null,
    "location": "Avenida Edison Passos, Alto da Boa Vista, Rio de Janeiro - RJ, 20531-077, Brasil",
    "manufacturer": null,
    "observations": null,
    "quantity": 1,
    "created_at": "2025-12-29T16:34:44.142166-03:00",
    "updated_at": "2025-12-29T16:34:44.142166-03:00",
    "installation_date": null,
    "year": null,
    "condition": "perfeitas condições de uso",
    "power": "230/255 kVA",
    "voltage": "220V"
  },
  {
    "id": "61c2db1a-01ab-4a05-9bb8-babe670e3f0d",
    "user_id": "c24ccbfe-b964-4c85-8708-0fc86a4e07a8",
    "contract_id": "c5d364e1-729a-4748-b657-d68457efedcd",
    "type": "Subestações de Energia Elétrica e Equipamentos Associados",
    "model": "Não especificado",
    "serial_number": "Não especificado",
    "location": "Unidades SESC listadas no contrato",
    "manufacturer": "Não especificado",
    "observations": null,
    "quantity": 1,
    "created_at": "2025-12-29T16:38:04.176578-03:00",
    "updated_at": "2025-12-29T16:38:04.176578-03:00",
    "installation_date": null,
    "year": "Não especificado",
    "condition": "Não especificado",
    "power": "Não especificado",
    "voltage": "Não especificado"
  },
  {
    "id": "85494660-da60-49f9-8b3b-5171d9313d48",
    "user_id": "c24ccbfe-b964-4c85-8708-0fc86a4e07a8",
    "contract_id": "54f88493-aa12-49ad-b9ab-bd3ec6466faf",
    "type": "Gerador",
    "model": "0300005319",
    "serial_number": null,
    "location": "Avenida Brasil, 4036, Manguinhos, Rio de Janeiro",
    "manufacturer": "STEMAC",
    "observations": null,
    "quantity": 1,
    "created_at": "2025-12-29T16:39:34.565617-03:00",
    "updated_at": "2025-12-29T16:39:34.565617-03:00",
    "installation_date": null,
    "year": null,
    "condition": null,
    "power": "300KVA",
    "voltage": "220V"
  },
  {
    "id": "a77a3d13-bbd8-4db3-8407-f8d7021776a7",
    "user_id": "c24ccbfe-b964-4c85-8708-0fc86a4e07a8",
    "contract_id": "237e90b1-f7d5-4167-af84-20a432f09ce8",
    "type": "Grupos Geradores de Energia",
    "model": "Não especificado",
    "serial_number": "Não especificado",
    "location": "Hospital Federal de Bonsucesso – Rio de Janeiro",
    "manufacturer": "Não especificado",
    "observations": null,
    "quantity": 1,
    "created_at": "2025-12-29T16:45:58.687536-03:00",
    "updated_at": "2025-12-29T16:45:58.687536-03:00",
    "installation_date": null,
    "year": "Não especificado",
    "condition": "Não especificado",
    "power": "750 kVA",
    "voltage": "Não especificado"
  },
  {
    "id": "ab3e485a-c9e8-4d6d-9013-41870a2b8078",
    "user_id": "c24ccbfe-b964-4c85-8708-0fc86a4e07a8",
    "contract_id": "0115fd34-4561-4b88-bf8e-d609364d45c8",
    "type": "Gerador de energia",
    "model": null,
    "serial_number": null,
    "location": "R MARIA SOARES SENDAS, 111 – VENDA VELHA - SÃO JOAO MERITI RJ, 25581-325",
    "manufacturer": null,
    "observations": null,
    "quantity": 1,
    "created_at": "2025-12-29T16:47:16.70135-03:00",
    "updated_at": "2025-12-29T16:47:16.70135-03:00",
    "installation_date": null,
    "year": null,
    "condition": "perfeitas condições de uso",
    "power": "500 kVA",
    "voltage": "380V"
  },
  {
    "id": "d30352b8-25d9-466e-880d-2ec1ebf5d9a0",
    "user_id": "c24ccbfe-b964-4c85-8708-0fc86a4e07a8",
    "contract_id": "fdb129d7-efff-43a9-b247-76240acdff56",
    "type": "Gerador de Energia Elétrica",
    "model": null,
    "serial_number": null,
    "location": "Avenida Engenheiro Sousa Filho, Jacarepaguá, Rio de Janeiro - RJ, 22753-039, Brasil",
    "manufacturer": null,
    "observations": null,
    "quantity": 1,
    "created_at": "2025-12-29T16:49:59.559959-03:00",
    "updated_at": "2025-12-29T16:49:59.559959-03:00",
    "installation_date": null,
    "year": null,
    "condition": null,
    "power": "150 kVA",
    "voltage": "220V"
  },
  {
    "id": "3526e72e-f9ee-465c-8aba-3049ac354993",
    "user_id": "c24ccbfe-b964-4c85-8708-0fc86a4e07a8",
    "contract_id": "de501486-3bea-4b39-93b8-78fc84ac1333",
    "type": "Gerador de energia",
    "model": null,
    "serial_number": null,
    "location": "Cajú, RJ",
    "manufacturer": null,
    "observations": null,
    "quantity": 1,
    "created_at": "2025-12-29T16:51:19.269978-03:00",
    "updated_at": "2025-12-29T16:51:19.269978-03:00",
    "installation_date": null,
    "year": null,
    "condition": "perfeitas condições de uso",
    "power": "150 kVA",
    "voltage": "380V"
  },
  {
    "id": "21394947-1377-4209-ba82-3eb924c9231c",
    "user_id": "c24ccbfe-b964-4c85-8708-0fc86a4e07a8",
    "contract_id": "13848adb-4348-4755-9f17-2b6ca70f2fb7",
    "type": "Gerador",
    "model": null,
    "serial_number": null,
    "location": "Rua Humberto de Campos, 774, Leblon, Rio de Janeiro",
    "manufacturer": null,
    "observations": null,
    "quantity": 1,
    "created_at": "2025-12-29T17:00:11.8429-03:00",
    "updated_at": "2025-12-29T17:00:11.8429-03:00",
    "installation_date": null,
    "year": null,
    "condition": null,
    "power": "12 kVA",
    "voltage": "220/127V"
  },
  {
    "id": "08b2d284-04f6-4ac9-afc5-76e10276669c",
    "user_id": "c24ccbfe-b964-4c85-8708-0fc86a4e07a8",
    "contract_id": "1318bfba-8fbb-4762-803b-1cb9d11f05c5",
    "type": "Quadro de Transferência Automática",
    "model": "800A",
    "serial_number": null,
    "location": "Estr. São Lourenço, 2040 - Figueira, Duque de Caxias - RJ, 25230-022",
    "manufacturer": null,
    "observations": null,
    "quantity": 1,
    "created_at": "2025-12-29T17:01:54.015153-03:00",
    "updated_at": "2025-12-29T17:01:54.015153-03:00",
    "installation_date": null,
    "year": null,
    "condition": "perfeitas condições de uso",
    "power": null,
    "voltage": null
  },
  {
    "id": "3e51b5b2-0d9d-4436-a8b7-b5c0bace10ce",
    "user_id": "c24ccbfe-b964-4c85-8708-0fc86a4e07a8",
    "contract_id": "c0118cf7-fa5c-4c6e-969a-7fc1df7cf556",
    "type": "Gerador de Energia",
    "model": null,
    "serial_number": null,
    "location": "Mantiquira, Duque de Caxias - RJ, 25250-170, Brasil",
    "manufacturer": null,
    "observations": null,
    "quantity": 1,
    "created_at": "2025-12-29T17:05:13.886471-03:00",
    "updated_at": "2025-12-29T17:05:13.886471-03:00",
    "installation_date": null,
    "year": null,
    "condition": "perfeitas condições de uso",
    "power": "115kVA",
    "voltage": "220V"
  },
  {
    "id": "e6777095-8e27-4328-abd0-ea66280088d6",
    "user_id": "c24ccbfe-b964-4c85-8708-0fc86a4e07a8",
    "contract_id": "e6d4f33f-2f96-409c-9f75-092906b64c23",
    "type": "gerador de energia",
    "model": null,
    "serial_number": null,
    "location": "Estr. São Lourenço 1939- Chácaras Rio-Petrópolis – cep 25243-150 / Armazém ARM",
    "manufacturer": null,
    "observations": null,
    "quantity": 1,
    "created_at": "2025-12-29T17:07:19.26852-03:00",
    "updated_at": "2025-12-29T17:07:19.26852-03:00",
    "installation_date": null,
    "year": null,
    "condition": null,
    "power": "220 kVA",
    "voltage": "220V"
  },
  {
    "id": "4db5ace0-47a4-4fe1-abcc-94a4fc8a9ab9",
    "user_id": "c24ccbfe-b964-4c85-8708-0fc86a4e07a8",
    "contract_id": "8a23ac2d-b862-4a5c-9d9b-4b7c01c387de",
    "type": "Quadro de Transferência Automático",
    "model": "QTA 800A",
    "serial_number": null,
    "location": "Local da Instalação (endereço do cliente)",
    "manufacturer": null,
    "observations": null,
    "quantity": 1,
    "created_at": "2025-12-29T17:09:42.717154-03:00",
    "updated_at": "2025-12-29T17:09:42.717154-03:00",
    "installation_date": null,
    "year": null,
    "condition": "em perfeitas condições",
    "power": null,
    "voltage": "220V"
  },
  {
    "id": "9bc635cc-fa32-4342-b85c-872447c7c861",
    "user_id": "c24ccbfe-b964-4c85-8708-0fc86a4e07a8",
    "contract_id": "f9123fd5-59c8-4e9b-88e9-af09979b7a3a",
    "type": "Gerador de energia elétrica a diesel",
    "model": "Não informado",
    "serial_number": null,
    "location": "Instalações da administração pública do Município de Mesquita",
    "manufacturer": null,
    "observations": null,
    "quantity": 1,
    "created_at": "2025-12-22T16:53:28.700091-03:00",
    "updated_at": "2026-01-05T15:30:23.628935-03:00",
    "installation_date": null,
    "year": null,
    "condition": null,
    "power": "80KVA",
    "voltage": "220V, 380V, 440V"
  },
  {
    "id": "39ae9548-6ad4-40dd-8968-2ddb1ebae6be",
    "user_id": "c24ccbfe-b964-4c85-8708-0fc86a4e07a8",
    "contract_id": "c31568a9-c0e9-4ae4-bc1b-0ba9ddc142c8",
    "type": "Gerador de energia",
    "model": "35 kVA",
    "serial_number": null,
    "location": "R FELIX LOPES COELHO, 222 – ILHA DA MADEIRA – ITAGUAI RJ – 23826-580",
    "manufacturer": "PRAMAC",
    "observations": null,
    "quantity": 1,
    "created_at": "2025-12-22T16:44:04.220451-03:00",
    "updated_at": "2026-01-05T15:39:01.183757-03:00",
    "installation_date": null,
    "year": null,
    "condition": "em perfeitas condições de uso",
    "power": "35 kVA",
    "voltage": "220V"
  },
  {
    "id": "9f671a88-9cd6-48a0-bf81-bae209838101",
    "user_id": "c24ccbfe-b964-4c85-8708-0fc86a4e07a8",
    "contract_id": "07b6e0e8-3a4f-4182-9e6c-903d87d15f23",
    "type": "Grupo gerador de energia",
    "model": "Não informado",
    "serial_number": null,
    "location": "Rua Felix Lopes Coelho, 222, Ilha da Madeira, Itaguaí -RJ",
    "manufacturer": null,
    "observations": null,
    "quantity": 1,
    "created_at": "2025-12-22T16:39:15.91131-03:00",
    "updated_at": "2026-01-05T15:48:58.928466-03:00",
    "installation_date": null,
    "year": null,
    "condition": null,
    "power": null,
    "voltage": "220V"
  },
  {
    "id": "5e686831-8ed3-41ed-ad4c-581d5a6ee4b7",
    "user_id": "c24ccbfe-b964-4c85-8708-0fc86a4e07a8",
    "contract_id": "a443c20d-3f0d-4b59-a1e7-8e3ff440437b",
    "type": "Grupo Gerador",
    "model": "1000kva, 560kva, 150kva",
    "serial_number": null,
    "location": "Múltiplas localizações",
    "manufacturer": null,
    "observations": null,
    "quantity": 1,
    "created_at": "2025-12-29T16:58:00.711988-03:00",
    "updated_at": "2026-01-05T16:21:48.317345-03:00",
    "installation_date": null,
    "year": null,
    "condition": "em perfeitas condições de uso",
    "power": "1000 kVA, 560 kVA, 150 kVA (x2)",
    "voltage": "220V"
  },
  {
    "id": "11afa241-e2e6-4197-9c95-949374c953bb",
    "user_id": "c24ccbfe-b964-4c85-8708-0fc86a4e07a8",
    "contract_id": "f5e35434-16ab-46c3-8bd2-945b6f1e8bb1",
    "type": "Grupo Gerador",
    "model": "Motor: DC1648A, Gerador: GTA 312AIIB B35T",
    "serial_number": "Motor: 1078692, Gerador: 1000874902",
    "location": "AV. BRASIL, 22346 - RIO DE JANEIRO RJ",
    "manufacturer": "SCANIA / WEG",
    "observations": null,
    "quantity": 1,
    "created_at": "2025-12-23T14:52:08.066424-03:00",
    "updated_at": "2026-01-05T16:27:23.194811-03:00",
    "installation_date": null,
    "year": null,
    "condition": null,
    "power": "700 kVA",
    "voltage": null
  },
  {
    "id": "73dadc99-3d83-42dc-9b53-6ed490ea0595",
    "user_id": "c24ccbfe-b964-4c85-8708-0fc86a4e07a8",
    "contract_id": "4e582962-b17e-424d-b785-20e2a01ba12e",
    "type": "gerador de energia",
    "model": "Não informado",
    "serial_number": null,
    "location": "R BARAO DA GAMBOA, 98 - GAMBOA, RIO DE JANEIRO RJ, 20220-690",
    "manufacturer": null,
    "observations": null,
    "quantity": 1,
    "created_at": "2025-12-23T14:48:36.528401-03:00",
    "updated_at": "2026-01-05T16:54:15.249635-03:00",
    "installation_date": null,
    "year": null,
    "condition": "usado",
    "power": "150 kVA",
    "voltage": "220V"
  },
  {
    "id": "193cf546-2f4e-41b9-83d5-0bc16fa1250a",
    "user_id": "c24ccbfe-b964-4c85-8708-0fc86a4e07a8",
    "contract_id": "f575de63-3391-43e0-b0fd-e1ada053b19f",
    "type": "Gerador de Energia",
    "model": "Não informado",
    "serial_number": null,
    "location": "Instalações RJ",
    "manufacturer": null,
    "observations": null,
    "quantity": 1,
    "created_at": "2025-12-23T13:30:15.012194-03:00",
    "updated_at": "2026-01-05T17:13:09.891043-03:00",
    "installation_date": null,
    "year": null,
    "condition": null,
    "power": "150kva",
    "voltage": "220v"
  },
  {
    "id": "546b6e1a-7061-49c1-b948-f2b44de7912a",
    "user_id": "c24ccbfe-b964-4c85-8708-0fc86a4e07a8",
    "contract_id": "4f76f45d-0bc6-41b3-b0d1-9a51ebf13890",
    "type": "Gerador",
    "model": "Não informado",
    "serial_number": null,
    "location": "Rua do Monjolo, 536, Loja - Pitangueiras, Rio de Janeiro - RJ, 21.930-376",
    "manufacturer": null,
    "observations": null,
    "quantity": 1,
    "created_at": "2025-12-22T17:36:58.940417-03:00",
    "updated_at": "2026-01-05T17:23:37.483533-03:00",
    "installation_date": null,
    "year": null,
    "condition": null,
    "power": "70 kVA",
    "voltage": null
  },
  {
    "id": "167b0b8a-34cf-4a38-8b5d-430c8214d1ec",
    "user_id": "c24ccbfe-b964-4c85-8708-0fc86a4e07a8",
    "contract_id": "f83cfad9-3df0-4d12-943c-91a6e6dceb4c",
    "type": "gerador de energia",
    "model": "Não informado",
    "serial_number": null,
    "location": "EST TEOTONIO FERREIRA DE ARAUJO, 355 – HANGAR 04 - FAROL DE SAO THOME - CAMPOS DOS GOYTACAZES – 28140-000",
    "manufacturer": null,
    "observations": null,
    "quantity": 1,
    "created_at": "2025-12-22T17:31:53.235559-03:00",
    "updated_at": "2026-01-05T17:30:35.156986-03:00",
    "installation_date": null,
    "year": null,
    "condition": "em perfeitas condições de uso",
    "power": "150 kVA",
    "voltage": "220V"
  },
  {
    "id": "3625cfc7-24f0-4c5c-bb1b-01d86ce2fdab",
    "user_id": "c24ccbfe-b964-4c85-8708-0fc86a4e07a8",
    "contract_id": "b717ffce-6a25-43d4-b432-3fea9e5ab87f",
    "type": "Gerador de Energia",
    "model": "Não informado",
    "serial_number": null,
    "location": "Estr. da Ilha, 870 - Guaratiba, Rio de Janeiro - RJ, 23020-230",
    "manufacturer": null,
    "observations": null,
    "quantity": 1,
    "created_at": "2025-12-22T17:11:37.28086-03:00",
    "updated_at": "2026-01-05T17:35:30.848005-03:00",
    "installation_date": null,
    "year": null,
    "condition": null,
    "power": "220 kVA",
    "voltage": "220V"
  },
  {
    "id": "6710a1a9-d38e-4304-b09d-3b778af39186",
    "user_id": "c24ccbfe-b964-4c85-8708-0fc86a4e07a8",
    "contract_id": "db4d1f43-a2e6-48ac-b134-de6e4e66b399",
    "type": "Gerador de energia elétrica a diesel",
    "model": "Não informado",
    "serial_number": null,
    "location": "Montado em Container super silenciado leve (SSL)",
    "manufacturer": null,
    "observations": null,
    "quantity": 1,
    "created_at": "2025-12-22T17:00:39.378599-03:00",
    "updated_at": "2026-01-05T18:02:27.568052-03:00",
    "installation_date": null,
    "year": null,
    "condition": "usado",
    "power": "Variável, incluindo 250 kVA e 350 kVA",
    "voltage": "220V, 380V, 440V"
  },
  {
    "id": "f27f689d-2547-4a82-b0c3-8ce9f9e936c4",
    "user_id": "c24ccbfe-b964-4c85-8708-0fc86a4e07a8",
    "contract_id": "8dd76a6a-afef-4122-8bb5-683c8ab4958f",
    "type": "Gerador de energia",
    "model": "Não informado",
    "serial_number": "Não informado",
    "location": "R HERCULANO PINHEIRO, 153 ARMAZENS 05B; 06B 07B E 08B; - PAVUNA – RIO DE JANEIRO RJ – 21532-440",
    "manufacturer": "Não informado",
    "observations": null,
    "quantity": 1,
    "created_at": "2025-12-19T16:05:11.517602-03:00",
    "updated_at": "2026-01-05T17:57:23.428012-03:00",
    "installation_date": null,
    "year": "Não informado",
    "condition": "em perfeitas condições de uso",
    "power": "1000 kVA",
    "voltage": "380V"
  },
  {
    "id": "f5c81719-dbcd-4884-8be2-27944529aea0",
    "user_id": "c24ccbfe-b964-4c85-8708-0fc86a4e07a8",
    "contract_id": "ce4f503c-9d6d-4393-bef9-da4626015358",
    "type": "Gerador",
    "model": "Não informado",
    "serial_number": null,
    "location": "Não informado",
    "manufacturer": null,
    "observations": null,
    "quantity": 1,
    "created_at": "2025-12-29T16:48:38.928736-03:00",
    "updated_at": "2026-01-21T15:06:17.726214-03:00",
    "installation_date": null,
    "year": null,
    "condition": null,
    "power": null,
    "voltage": null
  },
  {
    "id": "e6058c12-71f0-4ff8-aac8-bb30adf21488",
    "user_id": "c24ccbfe-b964-4c85-8708-0fc86a4e07a8",
    "contract_id": "97a2e772-ad86-4bb2-81e7-7fba7d117269",
    "type": "gerador trifásico",
    "model": "Não informado",
    "serial_number": null,
    "location": "Campus Centro",
    "manufacturer": null,
    "observations": null,
    "quantity": 1,
    "created_at": "2026-01-05T14:43:01.965122-03:00",
    "updated_at": "2026-01-05T15:56:00.853123-03:00",
    "installation_date": null,
    "year": null,
    "condition": null,
    "power": "180 kva",
    "voltage": "220/127v"
  },
  {
    "id": "5678a6bb-8206-4717-ad36-9748de0be5ee",
    "user_id": "c24ccbfe-b964-4c85-8708-0fc86a4e07a8",
    "contract_id": "19acaece-b0a5-4320-b275-59da287c6dce",
    "type": "Gerador de Energia Elétrica",
    "model": "Não informado",
    "serial_number": null,
    "location": "A ser definido pelo CONTRATANTE. Possíveis locais de instalação: Av. Venezuela, 110, Saúde, Rio de Janeiro/RJ ou Av. Salvador Alende, 5500, Recreio dos Bandeirantes, Rio de Janeiro/RJ.",
    "manufacturer": null,
    "observations": null,
    "quantity": 1,
    "created_at": "2026-01-05T14:33:29.516321-03:00",
    "updated_at": "2026-01-05T16:16:23.529435-03:00",
    "installation_date": null,
    "year": null,
    "condition": null,
    "power": null,
    "voltage": null
  },
  {
    "id": "dbfa40a9-a128-46cb-bda4-ae4b73969ba3",
    "user_id": "c24ccbfe-b964-4c85-8708-0fc86a4e07a8",
    "contract_id": "23e096c1-c533-4492-b6fd-3e22498e479c",
    "type": "Grupo Gerador",
    "model": "CTA G2",
    "serial_number": "30457535",
    "location": "AV MONROE, 810 – VILA ACTURA CAMPOS ELISEOS DUQUE DE CAXIAS RJ 25225-040",
    "manufacturer": "CUMMINS",
    "observations": null,
    "quantity": 1,
    "created_at": "2025-12-22T17:43:26.877979-03:00",
    "updated_at": "2026-01-05T17:20:19.758731-03:00",
    "installation_date": null,
    "year": null,
    "condition": null,
    "power": "230 kVA",
    "voltage": null
  },
  {
    "id": "6ce5d891-1a1b-42c5-9bcd-8cb021686122",
    "user_id": "c24ccbfe-b964-4c85-8708-0fc86a4e07a8",
    "contract_id": "47eeaf83-e80d-48ce-bc80-466252258ec8",
    "type": "Gerador",
    "model": "GDT50",
    "serial_number": null,
    "location": "Avenida Ayrton Senna, 4701- sala 211",
    "manufacturer": "Tivea",
    "observations": null,
    "quantity": 1,
    "created_at": "2025-12-22T16:34:36.388772-03:00",
    "updated_at": "2026-01-05T17:42:26.967277-03:00",
    "installation_date": null,
    "year": null,
    "condition": null,
    "power": null,
    "voltage": null
  },
  {
    "id": "2ebebad3-ec40-4a93-a69e-571120f0b5af",
    "user_id": "c24ccbfe-b964-4c85-8708-0fc86a4e07a8",
    "contract_id": "13856222-6c30-4edd-a881-ce899f892b72",
    "type": "Gerador",
    "model": "GEP 165-3",
    "serial_number": null,
    "location": "Estr. São Lorenço, 2040 - Figueira, Duque de Caxias/ RJ",
    "manufacturer": "Caterpillar",
    "observations": null,
    "quantity": 1,
    "created_at": "2026-01-07T15:59:59.349091-03:00",
    "updated_at": "2026-01-07T15:59:59.349091-03:00",
    "installation_date": null,
    "year": "2015",
    "condition": "usado",
    "power": "165 kVA",
    "voltage": null
  },
  {
    "id": "f7ebb9c0-8d66-495f-a411-0ebc1de1d760",
    "user_id": "c24ccbfe-b964-4c85-8708-0fc86a4e07a8",
    "contract_id": "d72e0fd3-f198-4768-aa9f-5569aafa56ca",
    "type": "QTA - Quadro de Transferência Automática",
    "model": "QTA 400A",
    "serial_number": null,
    "location": "Distribution Park - R. Dezesseis, S/N - Mantiquira, Duque de Caxias - RJ, 25250-61",
    "manufacturer": null,
    "observations": null,
    "quantity": 1,
    "created_at": "2026-01-07T16:09:09.517854-03:00",
    "updated_at": "2026-01-07T16:09:09.517854-03:00",
    "installation_date": null,
    "year": null,
    "condition": null,
    "power": null,
    "voltage": "220V"
  },
  {
    "id": "56defbd2-44f4-4c4a-b07e-8292dc935cd1",
    "user_id": "c24ccbfe-b964-4c85-8708-0fc86a4e07a8",
    "contract_id": "07750201-25ff-41f1-9eca-f5f87fffb5cd",
    "type": "Gerador de energia",
    "model": null,
    "serial_number": null,
    "location": "ESTR. SÃO LOURENÇO - DUQUE DE CAXIAS",
    "manufacturer": null,
    "observations": null,
    "quantity": 1,
    "created_at": "2026-01-07T16:11:37.607968-03:00",
    "updated_at": "2026-01-07T16:11:37.607968-03:00",
    "installation_date": null,
    "year": null,
    "condition": "Usado (em perfeitas condições de uso)",
    "power": "115 KVA",
    "voltage": "220V"
  },
  {
    "id": "b7f18a11-e546-465e-8fe7-1b67a3543b1a",
    "user_id": "c24ccbfe-b964-4c85-8708-0fc86a4e07a8",
    "contract_id": "53c3c92d-386b-4780-809e-310750ba15b6",
    "type": "Gerador de energia",
    "model": null,
    "serial_number": null,
    "location": "Estr. São Lourenço 2040- Chácaras Rio-Petrópolis – cep 25243-150 / Armazém ARM",
    "manufacturer": null,
    "observations": null,
    "quantity": 1,
    "created_at": "2026-01-07T16:14:48.853681-03:00",
    "updated_at": "2026-01-07T16:14:48.853681-03:00",
    "installation_date": null,
    "year": null,
    "condition": null,
    "power": "220 kVA",
    "voltage": "220V"
  },
  {
    "id": "cd0ec530-7a23-409f-b718-615db5515a4d",
    "user_id": "c24ccbfe-b964-4c85-8708-0fc86a4e07a8",
    "contract_id": "1b64179b-c190-40cd-9547-c1df80d0aa6e",
    "type": "Gerador de Energia",
    "model": "Não informado",
    "serial_number": null,
    "location": "Caxias - Capivari",
    "manufacturer": null,
    "observations": null,
    "quantity": 1,
    "created_at": "2025-12-29T17:13:01.962442-03:00",
    "updated_at": "2026-01-07T16:32:50.297511-03:00",
    "installation_date": null,
    "year": null,
    "condition": null,
    "power": "165kva",
    "voltage": "220V"
  },
  {
    "id": "2e6a0ede-6441-4350-91c1-2f7361b117e3",
    "user_id": "c24ccbfe-b964-4c85-8708-0fc86a4e07a8",
    "contract_id": "207b16fa-82fd-428c-bbd3-e0abd439b54f",
    "type": "Gerador",
    "model": null,
    "serial_number": null,
    "location": "Unidades Hospitalares, Unidades de Pronto Atendimento, Farmácia Central e Almoxarifado Central da Rede Municipal de Saúde de Cabo Frio",
    "manufacturer": null,
    "observations": null,
    "quantity": 1,
    "created_at": "2026-01-07T16:46:50.305052-03:00",
    "updated_at": "2026-01-07T16:54:51.060961-03:00",
    "installation_date": null,
    "year": null,
    "condition": null,
    "power": "260 kVA e 400 kVA",
    "voltage": null
  }
]